src/__init__.py
src/__pycache__/__init__.cpython-311.pyc
src/main/__init__.py
src/main/config.py
src/main/__pycache__/__init__.cpython-311.pyc
src/main/__pycache__/config.cpython-311.pyc
src/main/game/Board.py
src/main/game/Brain.py
src/main/game/DominoRound.py
src/main/game/Game.py
src/main/game/Hand.py
src/main/game/Piece.py
src/main/game/Player.py
src/main/game/Scorer.py
src/main/game/__init__.py
src/main/game/__pycache__/Board.cpython-311.pyc
src/main/game/__pycache__/Brain.cpython-311.pyc
src/main/game/__pycache__/DominoRound.cpython-311.pyc
src/main/game/__pycache__/Game.cpython-311.pyc
src/main/game/__pycache__/Hand.cpython-311.pyc
src/main/game/__pycache__/Piece.cpython-311.pyc
src/main/game/__pycache__/Player.cpython-311.pyc
src/main/game/__pycache__/Scorer.cpython-311.pyc
src/main/game/__pycache__/__init__.cpython-311.pyc
src/main/game/exceptions/Board.py
src/main/game/exceptions/Game.py
src/main/game/exceptions/Hand.py
src/main/game/exceptions/Scorer.py
src/main/game/exceptions/__init__.py
src/main/game/exceptions/__pycache__/Board.cpython-311.pyc
src/main/game/exceptions/__pycache__/Game.cpython-311.pyc
src/main/game/exceptions/__pycache__/Hand.cpython-311.pyc
src/main/game/exceptions/__pycache__/Scorer.cpython-311.pyc
src/main/game/exceptions/__pycache__/__init__.cpython-311.pyc
src/main/player/__pycache__/Brain.cpython-311.pyc
src/main/player/__pycache__/Hand.cpython-311.pyc
src/main/player/__pycache__/Player.cpython-311.pyc
src/main/player/__pycache__/__init__.cpython-311.pyc
src/main/server/Lobby.py
src/main/server/LobbyManager.py
src/main/server/__init__.py
src/main/server/app.py
src/main/server/exceptions/Lobby.py
src/main/server/exceptions/__init__.py
src/main/server/static/game.html
src/main/server/static/index.html
src/main/server/static/lobby.html
src/main/server/static/css/style.css
src/main/server/static/img/back.png
src/main/server/static/img/closed-blank.png
src/main/server/static/img/closed.png
src/main/server/static/img/d0.png
all_fives_domino-1.0.23.dist-info/LICENSE
all_fives_domino-1.0.23.dist-info/METADATA
all_fives_domino-1.0.23.dist-info/WHEEL
all_fives_domino-1.0.23.dist-info/top_level.txt
all_fives_domino-1.0.23.dist-info/RECORD
