Metadata-Version: 2.1
Name: all-fives-domino
Version: 1.0.23
Summary: Simple implementation of the All Fives domino variant
Home-page: https://github.com/Informanthik/all-fives-domino
Author: Jothapunkt
Author-email: jakob-hoefner@web.de
Requires-Python: >=3.8
License-File: LICENSE
Requires-Dist: jsons
Requires-Dist: flask
